fz_decrypt/__init__.py
fz_decrypt/core.py
fz_decrypt-0.1.1.dist-info/METADATA
fz_decrypt-0.1.1.dist-info/WHEEL
fz_decrypt-0.1.1.dist-info/top_level.txt
fz_decrypt-0.1.1.dist-info/RECORD
