Metadata-Version: 2.4
Name: fz-decrypt
Version: 0.1.1
Summary: A library to decrypt FileZilla-Client passwords protected by a master password.
Author: David Block
License: MIT
Project-URL: Homepage, https://github.com/deinusername/fz-decrypt-lib
Project-URL: Bug Tracker, https://github.com/deinusername/fz-decrypt-lib/issues
Keywords: filezilla,decrypt,password,security,recovery
Classifier: Development Status :: 4 - Beta
Classifier: Intended Audience :: Developers
Classifier: Programming Language :: Python :: 3
Classifier: Operating System :: OS Independent
Classifier: Topic :: Security :: Cryptography
Requires-Python: >=3.7
Requires-Dist: cryptography>=3.0
